larksuite/__init__.py
larksuite_py-0.0.1.dist-info/METADATA
larksuite_py-0.0.1.dist-info/WHEEL
larksuite_py-0.0.1.dist-info/top_level.txt
larksuite_py-0.0.1.dist-info/RECORD
